myprog_lib/__init__.py
myprog_lib/main.py
myprog_lib-0.1.0.dist-info/METADATA
myprog_lib-0.1.0.dist-info/WHEEL
myprog_lib-0.1.0.dist-info/top_level.txt
myprog_lib-0.1.0.dist-info/RECORD
